demo/__init__.py
demo/run.py
demo/test_android.py
demo/test_api.py
demo/test_image.py
demo/test_ios.py
demo/test_ocr.py
demo/test_web.py
demo/android_test/__init__.py
demo/android_test/run.py
demo/android_test/test_dir/__init__.py
demo/android_test/test_dir/test_android.py
demo/api_test/__init__.py
demo/api_test/run.py
demo/api_test/test_dir/__init__.py
demo/api_test/test_dir/test_api.py
demo/ios_test/__init__.py
demo/ios_test/run.py
demo/ios_test/test_dir/__init__.py
demo/ios_test/test_dir/test_ios.py
demo/page/__init__.py
demo/page/adr_page.py
demo/page/web_page.py
demo/screenshot/__init__.py
demo/tests/__init__.py
demo/tests/test_android.py
demo/tests/test_api.py
demo/tests/test_image.py
demo/tests/test_ios.py
demo/tests/test_ocr.py
demo/tests/test_web.py
demo/tests/case/__init__.py
demo/tests/case/test_android_pom.py
demo/tests/case/test_api.py
demo/tests/case/test_image.py
demo/tests/case/test_ios_normal.py
demo/tests/case/test_ocr.py
demo/tests/case/test_web_func.py
demo/tests/func/__init__.py
demo/tests/func/web_func.py
demo/tests/page/__init__.py
demo/tests/page/adr_page.py
demo/tests/page/web_page.py
demo/web_test/__init__.py
demo/web_test/run.py
demo/web_test/test_dir/__init__.py
demo/web_test/test_dir/test_web.py
qrunner/__init__.py
qrunner/case.py
qrunner/cli.py
qrunner/page.py
qrunner/scaffold.py
qrunner/core/__init__.py
qrunner/core/android/__init__.py
qrunner/core/android/case.py
qrunner/core/android/common.py
qrunner/core/android/driver.py
qrunner/core/android/element.py
qrunner/core/api/__init__.py
qrunner/core/api/case.py
qrunner/core/api/request.py
qrunner/core/h5/__init__.py
qrunner/core/h5/driver.py
qrunner/core/image/__init__.py
qrunner/core/image/element.py
qrunner/core/image/exceptions.py
qrunner/core/image/image_discern.py
qrunner/core/image/matching/__init__.py
qrunner/core/image/matching/keypoint/__init__.py
qrunner/core/image/matching/keypoint/base.py
qrunner/core/image/matching/keypoint/sift/__init__.py
qrunner-1.0.73.dist-info/METADATA
qrunner-1.0.73.dist-info/WHEEL
qrunner-1.0.73.dist-info/entry_points.txt
qrunner-1.0.73.dist-info/top_level.txt
qrunner-1.0.73.dist-info/RECORD
