Metadata-Version: 2.1
Name: qrunner
Version: 1.0.73
Summary: Api/Web/App端自动化测试框架
Home-page: https://gitee.com/bluepang2021/qrunner_new
Author: 杨康
Author-email: 772840356@qq.com
Platform: Android
Platform: IOS
Platform: Web
Platform: Api
Classifier: Programming Language :: Python :: 3.9
Requires-Python: >=3.7
Requires-Dist: tidevice (==0.6.1)
Requires-Dist: facebook-wda (==1.4.6)
Requires-Dist: uiautomator2 (==2.16.13)
Requires-Dist: selenium (==4.8.2)
Requires-Dist: webdriver-manager (==3.5.2)
Requires-Dist: pytest (==6.2.5)
Requires-Dist: pytest-rerunfailures (==10.2)
Requires-Dist: pytest-ordering (==0.6)
Requires-Dist: pytest-xdist (==2.5.0)
Requires-Dist: pytest-dependency (==0.5.1)
Requires-Dist: allure-pytest (==2.9.45)
Requires-Dist: jmespath (==0.9.5)
Requires-Dist: jsonschema (==4.17.0)
Requires-Dist: PyYAML (==6.0)
Provides-Extra: api
Requires-Dist: genson (==1.2.2) ; extra == 'api'
Requires-Dist: jsonschema (==4.17.0) ; extra == 'api'
Provides-Extra: db
Requires-Dist: PyMySQL (==0.10.1) ; extra == 'db'
Requires-Dist: pymongo (==4.0.1) ; extra == 'db'
Provides-Extra: encrypt
Requires-Dist: pycryptodome (==3.14.1) ; extra == 'encrypt'
Provides-Extra: excel
Requires-Dist: pandas (==1.3.4) ; extra == 'excel'
Requires-Dist: openpyxl (==3.0.9) ; extra == 'excel'
Requires-Dist: XlsxWriter (==3.0.2) ; extra == 'excel'
Provides-Extra: image
Requires-Dist: opencv-python (==4.6.0.66) ; extra == 'image'
Requires-Dist: opencv-contrib-python (==4.6.0.66) ; extra == 'image'
Requires-Dist: opencv-python-headless (==3.4.18.65) ; extra == 'image'
Provides-Extra: jira
Requires-Dist: jira (==3.1.1) ; extra == 'jira'
Provides-Extra: mail
Requires-Dist: yagmail (==0.15.293) ; extra == 'mail'
Provides-Extra: ocr
Requires-Dist: easyocr (==1.6.2) ; extra == 'ocr'
